pytracker3D/__init__.py
pytracker3D/calibration/__init__.py
pytracker3D/calibration/calibration.py
pytracker3D/calibration/calibration3D.py
pytracker3D/calibration/defineView.py
pytracker3D/calibration/selectmarkers.py
pytracker3D/calibration/test.py
pytracker3D/gui/Qt_2_py.py
pytracker3D/gui/__init__.py
pytracker3D/gui/pytracker3D.py
pytracker3D/gui/test.py
pytracker3D/gui/tracker_ui.py
pytracker3D/processing/__init__.py
pytracker3D/processing/postProcessing2D.py
pytracker3D/processing/postProcessing3D.py
pytracker3D/processing/trackanalyzer.py
pytracker3D/tracking/__init__.py
pytracker3D/tracking/videoTracking.py
pytracker3D/util/DLT.py
pytracker3D/util/__init__.py
pytracker3D/util/image_utils.py
pytracker3D-0.0.1.dist-info/LICENSE
pytracker3D-0.0.1.dist-info/METADATA
pytracker3D-0.0.1.dist-info/WHEEL
pytracker3D-0.0.1.dist-info/top_level.txt
pytracker3D-0.0.1.dist-info/RECORD
