Metadata-Version: 2.1
Name: pytracker3D
Version: 0.0.1
Summary: GUI and tools to track fish in 3D
Home-page: https://github.com/Fishified/pytracker3D
Author: Jason M Duguay
Author-email: duguay.jason@gmail.com
License: UNKNOWN
Platform: UNKNOWN
Classifier: Programming Language :: Python :: 3
Classifier: License :: OSI Approved :: MIT License
Classifier: Operating System :: OS Independent
